protectonce/__init__.py
protectonce/common_utils.py
protectonce/core_interface.py
protectonce/protect_once.py
protectonce/instrument/__init__.py
protectonce/instrument/base_interceptor.py
protectonce/instrument/class_interceptor.py
protectonce/instrument/method_interceptor.py
protectonce/instrument/po_exceptions.py
protectonce/rules/__init__.py
protectonce/rules/rules_manager.py
protectonce/rules/handlers/__init__.py
protectonce/rules/handlers/api.py
protectonce/rules/handlers/basic.py
protectonce/rules/handlers/bom_handler.py
protectonce/rules/handlers/cls.py
protectonce/rules/handlers/core_handler.py
protectonce/rules/handlers/http_server.py
protectonce/rules/handlers/rasp.py
protectonce/rules/handlers/runtime_handlers.py
protectonce/rules/handlers/virtual_module.py
protectonce/rules/types/__init__.py
protectonce/rules/types/base_rule.py
protectonce/rules/types/class_rule.py
protectonce/rules/types/handlers.py
protectonce/rules/types/method_rule.py
protectonce/rules/types/store.py
protectonce/rules/types/virtual_module_rule.py
protectonce/sdk/__init__.py
protectonce/sdk/user_monitoring.py
protectonce/utils/__init__.py
protectonce/utils/logger.py
protectonce-0.1.25.dist-info/LICENSE
protectonce-0.1.25.dist-info/METADATA
protectonce-0.1.25.dist-info/WHEEL
protectonce-0.1.25.dist-info/top_level.txt
protectonce-0.1.25.dist-info/RECORD
