Metadata-Version: 2.1
Name: protectonce
Version: 0.1.25
Summary: python agent package
Home-page: https://github.com/ProtectOnce/python_agent.git
Author: protectonce
Author-email: protectonce@protectonce.com
License: UNKNOWN
Platform: UNKNOWN
Classifier: Programming Language :: Python :: 3
Classifier: Operating System :: OS Independent
License-File: LICENSE
Requires-Dist: wrapt (==1.13.3)
Requires-Dist: orjson (==3.6.4)
Requires-Dist: protectonce-native (==0.1.25)
Requires-Dist: setuptools (==60.1.0)
